Metadata-Version: 2.1
Name: numering
Version: 0.9
Summary: UNKNOWN
Home-page: UNKNOWN
Author: sudo
License: MIT
Keywords: numering
Platform: UNKNOWN
License-File: LICENSE.rst
